aiosyslog/__init__.py
aiosyslog/__main__.py
aiosyslog/const.py
aiosyslog/exceptions.py
aiosyslog/helpers.py
aiosyslog/syslog_client.py
aiosyslog/tmpfile.py
aiosyslog-0.1.9.dist-info/licenses/LICENSE
aiosyslog-0.1.9.dist-info/METADATA
aiosyslog-0.1.9.dist-info/WHEEL
aiosyslog-0.1.9.dist-info/top_level.txt
aiosyslog-0.1.9.dist-info/RECORD
