Metadata-Version: 2.4
Name: aiosyslog
Version: 0.1.9
Summary: Async Syslog client
Author-email: Alexander Böhm <alxndr.boehm@gmail.com>, Ilya Tovbin <itovbin@fortinet.com>
License: BSD-2-Clause
Project-URL: Homepage, https://github.com/perceptionpoint/aiosyslog
Project-URL: Repository, https://github.com/perceptionpoint/aiosyslog
Requires-Python: >=3.9
License-File: LICENSE
Dynamic: license-file
